server/__main__.py
mcp_watson_discovery-0.1.10.dist-info/METADATA
mcp_watson_discovery-0.1.10.dist-info/WHEEL
mcp_watson_discovery-0.1.10.dist-info/entry_points.txt
mcp_watson_discovery-0.1.10.dist-info/top_level.txt
mcp_watson_discovery-0.1.10.dist-info/RECORD
