Metadata-Version: 2.4
Name: mcp-watson-discovery
Version: 0.1.10
Summary: MCP server for watson discovery
Author-email: Jose Castellanos <jose.castellanos.molina@ibm.com>
Project-URL: Homepage, https://github.com/matlock08/watson_discovery_mcp
Requires-Python: >=3.10
Requires-Dist: asyncio>=3.4.3
Requires-Dist: httpx>=0.28.1
Requires-Dist: ibm-watson>=9.0.0
Requires-Dist: mcp[cli]>=1.4.1
